stretched-goal/pcreg.sv
module pcreg #(
    parameter WIDTH = 32
)(
    // interface signals
    input   logic             clk,    // clock
    input   logic             rst,    // reset
    input   logic [WIDTH-1:0] immop,  // jump instruction pc
    input   logic             pcsrc,  // pc source
    output  logic [WIDTH-1:0] pc      // pc output
);

always_ff @ (posedge clk, posedge rst)
    if (rst) pc <= {WIDTH{1'b0}};
    else case(pcsrc)
        1'b0: pc <= pc + {{WIDTH-3{1'b0}}, 1'b1, {2{1'b0}}};
        1'b1: pc <= pc + immop;
        default: pc <= pc;
    endcase
        
        
endmodule

Lab4-Reduced-RISC-V/ControlUnit.sv
// ControlUnit is a decoder
// input:  32-bit instructions = instr
//         1-bit logic = EQ
// output: 1-bit control signals to other modules 

module ControlUnit (
    input  logic [6:0]             instr, 
    input  logic                   EQ, 
    output logic                   RegWrite, 
    output logic                   ALUctrl, 
    output logic                   ALUsrc, 
    output logic                   ImmSrc, 
    output logic                   PCsrc
); 

    logic   addi; 
    logic   bne; 

    // check opcode
    always_comb begin
        addi = 0;
        bne =  0;
        if ( instr[6:0] == 7'b0010011 ) begin //addi
            addi = 1; 
            bne = 0; 
        end
        else if ( instr[6:0] == 7'b1100011 ) begin //bne 
            addi = 0; 
            bne = 1; 
        end
    end
  
    // set output signals 
    always_comb  begin
        RegWrite = 1'b1; 
        ALUctrl = 1'b1; 
        ALUsrc = 1'b1; 
        ImmSrc = 1'b0; 
        PCsrc = 1'b0; 

        if (addi) begin
            RegWrite = 1'b1; 
            ALUctrl = 1'b1; 
            ALUsrc = 1'b1; 
            ImmSrc = 1'b0; 
            PCsrc = 1'b0; 
        end
        else if (bne) begin
            RegWrite = 1'b0; 
            ALUctrl = 1'b0; 
            ALUsrc = 1'b0; 
            ImmSrc = 1'b1; 
            if (EQ!=1'b1) PCsrc = 1'b1;
        end 

    end

endmodule

Lab4-Reduced-RISC-V/SignExtend.sv
// SignExtend Immediate
// input ImmSrc = 0 indicates 12-bit Imm = instr[31:20]
// input ImmSrc = 1 indicates 12-bit Imm = instr[31]+[7]+[30:25]+[11:8]
// output 32-bit ImmOp = sign extended Imm

module SignExtend #(
    parameter   DATA_WIDTH = 32, 
                IMM_WIDTH = 12
)(
    input  logic                     ImmSrc, 
    /* verilator lint_off UNUSED */
    input  logic  [31:0]             instr, 
    /* verilator lint_on UNUSED */
    output logic  [DATA_WIDTH-1:0]   ImmOp
); 

    logic  [IMM_WIDTH-1:0]  Imm1; 
    logic  [IMM_WIDTH-1:0]  Imm2;
    logic  [IMM_WIDTH-1:0]  Imm;  

    // reconstruct Imm
    assign Imm1 = {instr[31], instr[7], instr[30:25], instr[11:8]}; 
    assign Imm2 = instr[31:20]; 
    assign Imm = ImmSrc ? Imm1 : Imm2; 
    

    // sign extend
    assign ImmOp = { {20{Imm[IMM_WIDTH-1]}}, Imm[IMM_WIDTH-1:0]}; 

endmodule

Lab4-Reduced-RISC-V/reg_file.sv
module reg_file #(
    parameter       ADDRESS_WIDTH = 32,
                    DATA_WIDTH = 32
)(
    input logic               clk, //clock
    input logic [4:0]         AD1, AD2, AD3, //inputs rs1, rs2, rd
    input logic               WE3, //RegWrite
    input logic [ADDRESS_WIDTH-1:0]        WD3, //ALUout; to be written
    output logic [DATA_WIDTH-1:0]       RD1, RD2, //outputs
    output logic [DATA_WIDTH-1:0]       a0 // value stored in register location 1

);

logic [DATA_WIDTH-1:0] ram_array [2**ADDRESS_WIDTH-1:0];

always_ff @(posedge clk) begin
    if (WE3 == 1'b1)
        ram_array[AD3] <= WD3;
end

always_ff @(posedge clk) begin
    RD1 <= ram_array[AD1];
    RD2 <= ram_array[AD2];
end
    
assign a0 = ram_array[32'd10];

endmodule

Lab4-Reduced-RISC-V/alu.sv
module alu (
    /* verilator lint_off UNUSED */
    input logic                 ALUctrl,
    /* verilator lint_on UNUSED */
    input logic     [31:0]      ALUop1, ALUop2,
    output logic    [31:0]      ALUout,
    output logic                EQ

);

assign ALUout = ALUop1 + ALUop2;
assign EQ = (ALUop1 == ALUop2);

endmodule

Lab4-Reduced-RISC-V/mux2.sv
module mux2 (
    input logic [31:0]        RegOp2, ImmOp,//RD2 from Reg file; immediate value from instruction
    input logic              ALUsrc, //selector
    output logic [31:0]       ALUop2 //mux output  
);

assign ALUop2 = ALUsrc ? ImmOp : RegOp2;

endmodule

Lab4-Reduced-RISC-V/red_block.sv
module red_block #(  
    parameter   D_WIDTH = 32
)(
    input logic                     clk,            //MAIN INPUT CLK
    input logic     [4:0]           rs1,            //instr mem       rs1
    input logic     [4:0]           rs2,            //instr mem       rs2
    input logic     [4:0]           rd,             //instr mem       rd
    input logic                     ALUsrc,         //control unit    ALUsrc
    input logic                     ALUctrl,        //control unit    ALUctrl
    input logic     [D_WIDTH-1:0]   ImmOp,          //PCreg           Immop
    input logic                     RegWrite,       //control unit    RegWrite
    output logic                    EQ,             //control unit    EQ
    output logic    [D_WIDTH-1:0]   a0              //MAIN OUTPUT
); 

//connectiong wires
logic     [D_WIDTH-1:0]   ALUop1;        //RD1 to ALUop1
logic     [D_WIDTH-1:0]   regop2;        //RD2 to mux2
logic     [D_WIDTH-1:0]   ALUop2;        //mux2 to ALUop2
logic     [D_WIDTH-1:0]   ALUout;        //ALUsum to WD3

mux2 Mux2 (
    .RegOp2     (regop2),
    .ImmOp      (ImmOp),
    .ALUsrc     (ALUsrc),
    .ALUop2     (ALUop2)
); 

alu ALU(
    .ALUctrl    (ALUctrl),
    .ALUop1     (ALUop1),
    .ALUop2     (ALUop2),
    .ALUout     (ALUout),
    .EQ         (EQ)
); 

reg_file REG_FILE(
    .clk    (clk),
    .AD1    (rs1),
    .AD2    (rs2),
    .AD3    (rd),
    .WE3    (RegWrite),
    .WD3    (ALUout),
    .RD1    (ALUop1),
    .RD2    (regop2),
    .a0     (a0)
); 

endmodule

Lab4-Reduced-RISC-V/InstrMem.sv
// InstrMem is an asynchronous ROM
// read instructions from InstructionROM.mem file
// input: 32-bit address = A
// output: 32-bit instruction = RD

module InstrMem #(
    parameter   ADDRESS_WIDTH = 32, 
                DATA_WIDTH = 32
)(
    input   logic [ADDRESS_WIDTH-1:0] A, 
    output  logic [DATA_WIDTH-1:0]    RD
); 

logic [7:0] rom_array [2**ADDRESS_WIDTH-1:0]; 

initial begin
    $display("Loading rom."); 
    $readmemh("Instruction.mem", rom_array); 
end; 

assign RD = {rom_array[A+3], rom_array[A+2], rom_array[A+1], rom_array[A]} ; 

endmodule

Lab4-Reduced-RISC-V/rRISCV.sv
module rRISCV #(
    parameter D_WIDTH = 32
)(
    input logic     clk,
    input logic     rst,
    output logic [D_WIDTH-1:0]    a0
);

//connecting wires

logic   [D_WIDTH-1:0]   PC;             //PCReg to Instr Mem
logic   [D_WIDTH-1:0]   instr;          //InstrMem to control unit, reg file and sign extend
logic                   ALUctrl;        //Control Unit to red block
logic                   ALUsrc;         //Control Unit to red block
logic   [D_WIDTH-1:0]   ImmOp;          //sign extend to red block and pcreg
logic                   RegWrite;       //Control unit to reg file
logic                   EQ;             //alu to control unit
logic                   ImmSrc;         //Control unit to Sign extend
logic                   PCsrc;          //Control unit to PC_reg Mux

pcreg PCregister(
    .clk(clk),    // clock
    .rst(rst),    // reset
    .immop(ImmOp),  // jump instruction pc
    .pcsrc(PCsrc),  // pc source
    .pc(PC)
);

ControlUnit Control(
    .instr(instr[6:0]), 
    .EQ(EQ), 
    .RegWrite(RegWrite), 
    .ALUctrl(ALUctrl), 
    .ALUsrc(ALUsrc), 
    .ImmSrc(ImmSrc), 
    .PCsrc(PCsrc)
);


InstrMem InstrMem (
    .A (PC),
    .RD (instr)
); 

red_block RedBlock(
    .clk(clk),           //MAIN INPUT CLK
    .rs1(instr[19:15]),        //instr mem       rs1
    .rs2(instr[24:20]),        //instr mem       rs2
    .rd(instr[11:7]),        //instr mem       rd
    .ALUsrc(ALUsrc),        //control unit    ALUsrc
    .ALUctrl(ALUctrl),       //control unit    ALUctrl
    .ImmOp(ImmOp),         //PCreg           Immop
    .RegWrite(RegWrite),      //control unit    RegWrite
    .EQ(EQ),            //control unit    EQ
    .a0(a0)             //MAIN OUTPUT   
); 

SignExtend SignExtend (
    .ImmSrc     (ImmSrc),
    .instr      (instr),
    .ImmOp      (ImmOp)
); 

ControlUnit ControlUnit (
    .instr      (instr),
    .EQ         (EQ),
    .RegWrite   (RegWrite),
    .ALUctrl    (ALUctrl),
    .ALUsrc     (ALUsrc),
    .ImmSrc     (ImmSrc),
    .PCsrc      (PCsrc)
);

pcreg PC_Reg (
    .clk        (clk),
    .rst        (rst),
    .immop      (ImmOp),
    .pcsrc      (PCsrc),
    .pc         (PC)
);


endmodule

Lab4-Reduced-RISC-V/rRISCV.vcd
$version Generated by VerilatedVcd $end
$date Fri Nov 25 12:40:40 2022 $end
$timescale 1ps $end

 $scope module TOP $end
  $var wire 32 Y a0 [31:0] $end
  $var wire  1 W clk $end
  $var wire  1 X rst $end
  $scope module rRISCV $end
   $var wire  1 O ALUctrl $end
   $var wire  1 P ALUsrc $end
   $var wire 32 \ D_WIDTH [31:0] $end
   $var wire  1 Z EQ $end
   $var wire 32 Q ImmOp [31:0] $end
   $var wire  1 S ImmSrc $end
   $var wire 32 E PC [31:0] $end
   $var wire  1 T PCsrc $end
   $var wire  1 R RegWrite $end
   $var wire 32 Y a0 [31:0] $end
   $var wire  1 W clk $end
   $var wire 32 F instr [31:0] $end
   $var wire  1 X rst $end
   $scope module Control $end
    $var wire  1 O ALUctrl $end
    $var wire  1 P ALUsrc $end
    $var wire  1 Z EQ $end
    $var wire  1 S ImmSrc $end
    $var wire  1 T PCsrc $end
    $var wire  1 R RegWrite $end
    $var wire  1 H addi $end
    $var wire  1 I bne $end
    $var wire  7 G instr [6:0] $end
   $upscope $end
   $scope module InstrMem $end
    $var wire 32 E A [31:0] $end
    $var wire 32 \ ADDRESS_WIDTH [31:0] $end
    $var wire 32 \ DATA_WIDTH [31:0] $end
    $var wire 32 F RD [31:0] $end
   $upscope $end
   $scope module PC_Reg $end
    $var wire 32 \ WIDTH [31:0] $end
    $var wire  1 W clk $end
    $var wire 32 Q immop [31:0] $end
    $var wire 32 E pc [31:0] $end
    $var wire  1 T pcsrc $end
    $var wire  1 X rst $end
   $upscope $end
   $scope module PCregister $end
    $var wire 32 \ WIDTH [31:0] $end
    $var wire  1 W clk $end
    $var wire 32 Q immop [31:0] $end
    $var wire 32 E pc [31:0] $end
    $var wire  1 T pcsrc $end
    $var wire  1 X rst $end
   $upscope $end
   $scope module RedBlock $end
    $var wire  1 O ALUctrl $end
    $var wire 32 # ALUop1 [31:0] $end
    $var wire 32 U ALUop2 [31:0] $end
    $var wire 32 [ ALUout [31:0] $end
    $var wire  1 P ALUsrc $end
    $var wire 32 \ D_WIDTH [31:0] $end
    $var wire  1 Z EQ $end
    $var wire 32 Q ImmOp [31:0] $end
    $var wire  1 R RegWrite $end
    $var wire 32 Y a0 [31:0] $end
    $var wire  1 W clk $end
    $var wire  5 L rd [4:0] $end
    $var wire 32 $ regop2 [31:0] $end
    $var wire  5 J rs1 [4:0] $end
    $var wire  5 K rs2 [4:0] $end
    $scope module ALU $end
     $var wire  1 O ALUctrl $end
     $var wire 32 # ALUop1 [31:0] $end
     $var wire 32 U ALUop2 [31:0] $end
     $var wire 32 [ ALUout [31:0] $end
     $var wire  1 Z EQ $end
    $upscope $end
    $scope module Mux2 $end
     $var wire 32 U ALUop2 [31:0] $end
     $var wire  1 P ALUsrc $end
     $var wire 32 Q ImmOp [31:0] $end
     $var wire 32 $ RegOp2 [31:0] $end
    $upscope $end
    $scope module REG_FILE $end
     $var wire  5 J AD1 [4:0] $end
     $var wire  5 K AD2 [4:0] $end
     $var wire  5 L AD3 [4:0] $end
     $var wire 32 ] ADDRESS_WIDTH [31:0] $end
     $var wire 32 \ DATA_WIDTH [31:0] $end
     $var wire 32 # RD1 [31:0] $end
     $var wire 32 $ RD2 [31:0] $end
     $var wire 32 [ WD3 [31:0] $end
     $var wire  1 R WE3 $end
     $var wire 32 Y a0 [31:0] $end
     $var wire  1 W clk $end
     $var wire 32 % ram_array[0] [31:0] $end
     $var wire 32 / ram_array[10] [31:0] $end
     $var wire 32 0 ram_array[11] [31:0] $end
     $var wire 32 1 ram_array[12] [31:0] $end
     $var wire 32 2 ram_array[13] [31:0] $end
     $var wire 32 3 ram_array[14] [31:0] $end
     $var wire 32 4 ram_array[15] [31:0] $end
     $var wire 32 5 ram_array[16] [31:0] $end
     $var wire 32 6 ram_array[17] [31:0] $end
     $var wire 32 7 ram_array[18] [31:0] $end
     $var wire 32 8 ram_array[19] [31:0] $end
     $var wire 32 & ram_array[1] [31:0] $end
     $var wire 32 9 ram_array[20] [31:0] $end
     $var wire 32 : ram_array[21] [31:0] $end
     $var wire 32 ; ram_array[22] [31:0] $end
     $var wire 32 < ram_array[23] [31:0] $end
     $var wire 32 = ram_array[24] [31:0] $end
     $var wire 32 > ram_array[25] [31:0] $end
     $var wire 32 ? ram_array[26] [31:0] $end
     $var wire 32 @ ram_array[27] [31:0] $end
     $var wire 32 A ram_array[28] [31:0] $end
     $var wire 32 B ram_array[29] [31:0] $end
     $var wire 32 ' ram_array[2] [31:0] $end
     $var wire 32 C ram_array[30] [31:0] $end
     $var wire 32 D ram_array[31] [31:0] $end
     $var wire 32 ( ram_array[3] [31:0] $end
     $var wire 32 ) ram_array[4] [31:0] $end
     $var wire 32 * ram_array[5] [31:0] $end
     $var wire 32 + ram_array[6] [31:0] $end
     $var wire 32 , ram_array[7] [31:0] $end
     $var wire 32 - ram_array[8] [31:0] $end
     $var wire 32 . ram_array[9] [31:0] $end
    $upscope $end
   $upscope $end
   $scope module SignExtend $end
    $var wire 32 \ DATA_WIDTH [31:0] $end
    $var wire 32 ^ IMM_WIDTH [31:0] $end
    $var wire 12 V Imm [11:0] $end
    $var wire 12 M Imm1 [11:0] $end
    $var wire 12 N Imm2 [11:0] $end
    $var wire 32 Q ImmOp [31:0] $end
    $var wire  1 S ImmSrc $end
    $var wire 32 F instr [31:0] $end
   $upscope $end
  $upscope $end
 $upscope $end
$enddefinitions $end


#0
b00000000000000000000000000000000 #
b00000000000000000000000000000000 $
b00000000000000000000000000000000 %
b00000000000000000000000000000000 &
b00000000000000000000000000000000 '
b00000000000000000000000000000000 (
b00000000000000000000000000000000 )
b00000000000000000000000000000000 *
b00000000000000000000000000000000 +
b00000000000000000000000000000000 ,
b00000000000000000000000000000000 -
b00000000000000000000000000000000 .
b00000000000000000000000000000000 /
b00000000000000000000000000000000 0
b00000000000000000000000000000000 1
b00000000000000000000000000000000 2
b00000000000000000000000000000000 3
b00000000000000000000000000000000 4
b00000000000000000000000000000000 5
b00000000000000000000000000000000 6
b00000000000000000000000000000000 7
b00000000000000000000000000000000 8
b00000000000000000000000000000000 9
b00000000000000000000000000000000 :
b00000000000000000000000000000000 ;
b00000000000000000000000000000000 <
b00000000000000000000000000000000 =
b00000000000000000000000000000000 >
b00000000000000000000000000000000 ?
b00000000000000000000000000000000 @
b00000000000000000000000000000000 A
b00000000000000000000000000000000 B
b00000000000000000000000000000000 C
b00000000000000000000000000000000 D
b00000000000000000000000000000000 E
b00000000000000000000000000000000 F
b0000000 G
0H
0I
b00000 J
b00000 K
b00000 L
b000000000000 M
b000000000000 N
0O
0P
b00000000000000000000000000000000 Q
0R
0S
0T
b00000000000000000000000000000000 U
b000000000000 V
1W
0X
b00000000000000000000000000000000 Y
1Z
b00000000000000000000000000000000 [
b00000000000000000000000000100000 \
b00000000000000000000000000000101 ]
b00000000000000000000000000001100 ^
#1
b00001111111100000000001100010011 F
b0010011 G
1H
b11111 K
b00110 L
b000001110011 M
b000011111111 N
1O
1P
b00000000000000000000000011111111 Q
1R
b00000000000000000000000011111111 U
b000011111111 V
0W
0Z
b00000000000000000000000011111111 [
#2
b00000000000000000000000011111111 +
b00000000000000000000000000000100 E
b00000000000000000000010100010011 F
b00000 K
b01010 L
b000000000101 M
b000000000000 N
b00000000000000000000000000000000 Q
b00000000000000000000000000000000 U
b000000000000 V
1W
1Z
b00000000000000000000000000000000 [
#3
0W
#4
b00000000000000000000000000001000 E
b00000000000000000000010110010011 F
b01011 L
b010000000101 M
1W
#5
0W
#6
b00000000000000000000000000001100 E
b00000000000001011000010100010011 F
b01011 J
b01010 L
b000000000101 M
1W
#7
0W
#8
b00000000000000000000000000010000 E
b00000000000101011000010110010011 F
b00001 K
b01011 L
b010000000101 M
b000000000001 N
b00000000000000000000000000000001 Q
b00000000000000000000000000000001 U
b000000000001 V
1W
0Z
b00000000000000000000000000000001 [
#9
0W
#10
b00000000000000000000000000000001 0
b00000000000000000000000000010100 E
b11111110011001011001100011100011 F
b1100011 G
0H
1I
b00110 K
b10001 L
b111111111000 M
b111111100110 N
0O
0P
b11111111111111111111111111111000 Q
0R
1S
b00000000000000000000000000000000 U
b111111111000 V
1W
1Z
b00000000000000000000000000000000 [
#11
0W
#12
b00000000000000000000000000000001 #
b00000000000000000000000011111111 $
b00000000000000000000000000011000 E
b11111110000000110001000011100011 F
b00110 J
b00000 K
b00001 L
b111111110000 M
b111111100000 N
b11111111111111111111111111110000 Q
1T
b00000000000000000000000011111111 U
b111111110000 V
1W
0Z
b00000000000000000000000100000000 [
#13
0W
#14
b00000000000000000000000011111111 #
b00000000000000000000000000000000 $
b00000000000000000000000000001000 E
b00000000000000000000010110010011 F
b0010011 G
1H
0I
b00000 J
b01011 L
b010000000101 M
b000000000000 N
1O
1P
b00000000000000000000000000000000 Q
1R
0S
0T
b00000000000000000000000000000000 U
b000000000000 V
1W
b00000000000000000000000011111111 [
#15
0W
#16
b00000000000000000000000000000000 #
b00000000000000000000000011111111 0
b00000000000000000000000000001100 E
b00000000000001011000010100010011 F
b01011 J
b01010 L
b000000000101 M
1W
1Z
b00000000000000000000000000000000 [
#17
0W
#18
b00000000000000000000000011111111 #
b00000000000000000000000000010000 E
b00000000000101011000010110010011 F
b00001 K
b01011 L
b010000000101 M
b000000000001 N
b00000000000000000000000000000001 Q
b00000000000000000000000000000001 U
b000000000001 V
1W
0Z
b00000000000000000000000100000000 [
#19
0W
#20
b00000000000000000000000100000000 0
b00000000000000000000000000010100 E
b11111110011001011001100011100011 F
b1100011 G
0H
1I
b00110 K
b10001 L
b111111111000 M
b111111100110 N
0O
0P
b11111111111111111111111111111000 Q
0R
1S
1T
b00000000000000000000000000000000 U
b111111111000 V
1W
b00000000000000000000000011111111 [
#21
0W
#22
b00000000000000000000000100000000 #
b00000000000000000000000011111111 $
b00000000000000000000000000001100 E
b00000000000001011000010100010011 F
b0010011 G
1H
0I
b00000 K
b01010 L
b000000000101 M
b000000000000 N
1O
1P
b00000000000000000000000000000000 Q
1R
0S
0T
b000000000000 V
1W
b00000000000000000000000100000000 [
#23
0W
#24
b00000000000000000000000000000000 $
b00000000000000000000000100000000 /
b00000000000000000000000000010000 E
b00000000000101011000010110010011 F
b00001 K
b01011 L
b010000000101 M
b000000000001 N
b00000000000000000000000000000001 Q
b00000000000000000000000000000001 U
b000000000001 V
1W
b00000000000000000000000100000000 Y
b00000000000000000000000100000001 [
#25
0W
#26
b00000000000000000000000100000001 0
b00000000000000000000000000010100 E
b11111110011001011001100011100011 F
b1100011 G
0H
1I
b00110 K
b10001 L
b111111111000 M
b111111100110 N
0O
0P
b11111111111111111111111111111000 Q
0R
1S
1T
b00000000000000000000000000000000 U
b111111111000 V
1W
b00000000000000000000000100000000 [
#27
0W
#28
b00000000000000000000000100000001 #
b00000000000000000000000011111111 $
b00000000000000000000000000001100 E
b00000000000001011000010100010011 F
b0010011 G
1H
0I
b00000 K
b01010 L
b000000000101 M
b000000000000 N
1O
1P
b00000000000000000000000000000000 Q
1R
0S
0T
b000000000000 V
1W
b00000000000000000000000100000001 [
#29
0W
#30
b00000000000000000000000000000000 $
b00000000000000000000000100000001 /
b00000000000000000000000000010000 E
b00000000000101011000010110010011 F
b00001 K
b01011 L
b010000000101 M
b000000000001 N
b00000000000000000000000000000001 Q
b00000000000000000000000000000001 U
b000000000001 V
1W
b00000000000000000000000100000001 Y
b00000000000000000000000100000010 [
#31
0W
#32
b00000000000000000000000100000010 0
b00000000000000000000000000010100 E
b11111110011001011001100011100011 F
b1100011 G
0H
1I
b00110 K
b10001 L
b111111111000 M
b111111100110 N
0O
0P
b11111111111111111111111111111000 Q
0R
1S
1T
b00000000000000000000000000000000 U
b111111111000 V
1W
b00000000000000000000000100000001 [
#33
0W
#34
b00000000000000000000000100000010 #
b00000000000000000000000011111111 $
b00000000000000000000000000001100 E
b00000000000001011000010100010011 F
b0010011 G
1H
0I
b00000 K
b01010 L
b000000000101 M
b000000000000 N
1O
1P
b00000000000000000000000000000000 Q
1R
0S
0T
b000000000000 V
1W
b00000000000000000000000100000010 [
#35
0W
#36
b00000000000000000000000000000000 $
b00000000000000000000000100000010 /
b00000000000000000000000000010000 E
b00000000000101011000010110010011 F
b00001 K
b01011 L
b010000000101 M
b000000000001 N
b00000000000000000000000000000001 Q
b00000000000000000000000000000001 U
b000000000001 V
1W
b00000000000000000000000100000010 Y
b00000000000000000000000100000011 [
#37
0W
#38
b00000000000000000000000100000011 0
b00000000000000000000000000010100 E
b11111110011001011001100011100011 F
b1100011 G
0H
1I
b00110 K
b10001 L
b111111111000 M
b111111100110 N
0O
0P
b11111111111111111111111111111000 Q
0R
1S
1T
b00000000000000000000000000000000 U
b111111111000 V
1W
b00000000000000000000000100000010 [
#39
0W
#40
b00000000000000000000000100000011 #
b00000000000000000000000011111111 $
b00000000000000000000000000001100 E
b00000000000001011000010100010011 F
b0010011 G
1H
0I
b00000 K
b01010 L
b000000000101 M
b000000000000 N
1O
1P
b00000000000000000000000000000000 Q
1R
0S
0T
b000000000000 V
1W
b00000000000000000000000100000011 [
#41
0W
#42
b00000000000000000000000000000000 $
b00000000000000000000000100000011 /
b00000000000000000000000000010000 E
b00000000000101011000010110010011 F
b00001 K
b01011 L
b010000000101 M
b000000000001 N
b00000000000000000000000000000001 Q
b00000000000000000000000000000001 U
b000000000001 V
1W
b00000000000000000000000100000011 Y
b00000000000000000000000100000100 [
#43
0W
#44
b00000000000000000000000100000100 0
b00000000000000000000000000010100 E
b11111110011001011001100011100011 F
b1100011 G
0H
1I
b00110 K
b10001 L
b111111111000 M
b111111100110 N
0O
0P
b11111111111111111111111111111000 Q
0R
1S
1T
b00000000000000000000000000000000 U
b111111111000 V
1W
b00000000000000000000000100000011 [
#45
0W
#46
b00000000000000000000000100000100 #
b00000000000000000000000011111111 $
b00000000000000000000000000001100 E
b00000000000001011000010100010011 F
b0010011 G
1H
0I
b00000 K
b01010 L
b000000000101 M
b000000000000 N
1O
1P
b00000000000000000000000000000000 Q
1R
0S
0T
b000000000000 V
1W
b00000000000000000000000100000100 [
#47
0W
#48
b00000000000000000000000000000000 $
b00000000000000000000000100000100 /
b00000000000000000000000000010000 E
b00000000000101011000010110010011 F
b00001 K
b01011 L
b010000000101 M
b000000000001 N
b00000000000000000000000000000001 Q
b00000000000000000000000000000001 U
b000000000001 V
1W
b00000000000000000000000100000100 Y
b00000000000000000000000100000101 [
#49
0W
#50
b00000000000000000000000100000101 0
b00000000000000000000000000010100 E
b11111110011001011001100011100011 F
b1100011 G
0H
1I
b00110 K
b10001 L
b111111111000 M
b111111100110 N
0O
0P
b11111111111111111111111111111000 Q
0R
1S
1T
b00000000000000000000000000000000 U
b111111111000 V
1W
b00000000000000000000000100000100 [
#51
0W
#52
b00000000000000000000000100000101 #
b00000000000000000000000011111111 $
b00000000000000000000000000001100 E
b00000000000001011000010100010011 F
b0010011 G
1H
0I
b00000 K
b01010 L
b000000000101 M
b000000000000 N
1O
1P
b00000000000000000000000000000000 Q
1R
0S
0T
b000000000000 V
1W
b00000000000000000000000100000101 [
#53
0W
#54
b00000000000000000000000000000000 $
b00000000000000000000000100000101 /
b00000000000000000000000000010000 E
b00000000000101011000010110010011 F
b00001 K
b01011 L
b010000000101 M
b000000000001 N
b00000000000000000000000000000001 Q
b00000000000000000000000000000001 U
b000000000001 V
1W
b00000000000000000000000100000101 Y
b00000000000000000000000100000110 [
#55
0W
#56
b00000000000000000000000100000110 0
b00000000000000000000000000010100 E
b11111110011001011001100011100011 F
b1100011 G
0H
1I
b00110 K
b10001 L
b111111111000 M
b111111100110 N
0O
0P
b11111111111111111111111111111000 Q
0R
1S
1T
b00000000000000000000000000000000 U
b111111111000 V
1W
b00000000000000000000000100000101 [
#57
0W
#58
b00000000000000000000000100000110 #
b00000000000000000000000011111111 $
b00000000000000000000000000001100 E
b00000000000001011000010100010011 F
b0010011 G
1H
0I
b00000 K
b01010 L
b000000000101 M
b000000000000 N
1O
1P
b00000000000000000000000000000000 Q
1R
0S
0T
b000000000000 V
1W
b00000000000000000000000100000110 [
#59
0W
#60
b00000000000000000000000000000000 $
b00000000000000000000000100000110 /
b00000000000000000000000000010000 E
b00000000000101011000010110010011 F
b00001 K
b01011 L
b010000000101 M
b000000000001 N
b00000000000000000000000000000001 Q
b00000000000000000000000000000001 U
b000000000001 V
1W
b00000000000000000000000100000110 Y
b00000000000000000000000100000111 [
#61
0W
#62
b00000000000000000000000100000111 0
b00000000000000000000000000010100 E
b11111110011001011001100011100011 F
b1100011 G
0H
1I
b00110 K
b10001 L
b111111111000 M
b111111100110 N
0O
0P
b11111111111111111111111111111000 Q
0R
1S
1T
b00000000000000000000000000000000 U
b111111111000 V
1W
b00000000000000000000000100000110 [
#63
0W
#64
b00000000000000000000000100000111 #
b00000000000000000000000011111111 $
b00000000000000000000000000001100 E
b00000000000001011000010100010011 F
b0010011 G
1H
0I
b00000 K
b01010 L
b000000000101 M
b000000000000 N
1O
1P
b00000000000000000000000000000000 Q
1R
0S
0T
b000000000000 V
1W
b00000000000000000000000100000111 [
#65
0W
#66
b00000000000000000000000000000000 $
b00000000000000000000000100000111 /
b00000000000000000000000000010000 E
b00000000000101011000010110010011 F
b00001 K
b01011 L
b010000000101 M
b000000000001 N
b00000000000000000000000000000001 Q
b00000000000000000000000000000001 U
b000000000001 V
1W
b00000000000000000000000100000111 Y
b00000000000000000000000100001000 [
#67
0W
#68
b00000000000000000000000100001000 0
b00000000000000000000000000010100 E
b11111110011001011001100011100011 F
b1100011 G
0H
1I
b00110 K
b10001 L
b111111111000 M
b111111100110 N
0O
0P
b11111111111111111111111111111000 Q
0R
1S
1T
b00000000000000000000000000000000 U
b111111111000 V
1W
b00000000000000000000000100000111 [
#69
0W
#70
b00000000000000000000000100001000 #
b00000000000000000000000011111111 $
b00000000000000000000000000001100 E
b00000000000001011000010100010011 F
b0010011 G
1H
0I
b00000 K
b01010 L
b000000000101 M
b000000000000 N
1O
1P
b00000000000000000000000000000000 Q
1R
0S
0T
b000000000000 V
1W
b00000000000000000000000100001000 [
#71
0W
#72
b00000000000000000000000000000000 $
b00000000000000000000000100001000 /
b00000000000000000000000000010000 E
b00000000000101011000010110010011 F
b00001 K
b01011 L
b010000000101 M
b000000000001 N
b00000000000000000000000000000001 Q
b00000000000000000000000000000001 U
b000000000001 V
1W
b00000000000000000000000100001000 Y
b00000000000000000000000100001001 [
#73
0W
#74
b00000000000000000000000100001001 0
b00000000000000000000000000010100 E
b11111110011001011001100011100011 F
b1100011 G
0H
1I
b00110 K
b10001 L
b111111111000 M
b111111100110 N
0O
0P
b11111111111111111111111111111000 Q
0R
1S
1T
b00000000000000000000000000000000 U
b111111111000 V
1W
b00000000000000000000000100001000 [
#75
0W
#76
b00000000000000000000000100001001 #
b00000000000000000000000011111111 $
b00000000000000000000000000001100 E
b00000000000001011000010100010011 F
b0010011 G
1H
0I
b00000 K
b01010 L
b000000000101 M
b000000000000 N
1O
1P
b00000000000000000000000000000000 Q
1R
0S
0T
b000000000000 V
1W
b00000000000000000000000100001001 [
#77
0W
#78
b00000000000000000000000000000000 $
b00000000000000000000000100001001 /
b00000000000000000000000000010000 E
b00000000000101011000010110010011 F
b00001 K
b01011 L
b010000000101 M
b000000000001 N
b00000000000000000000000000000001 Q
b00000000000000000000000000000001 U
b000000000001 V
1W
b00000000000000000000000100001001 Y
b00000000000000000000000100001010 [
#79
0W
#80
b00000000000000000000000100001010 0
b00000000000000000000000000010100 E
b11111110011001011001100011100011 F
b1100011 G
0H
1I
b00110 K
b10001 L
b111111111000 M
b111111100110 N
0O
0P
b11111111111111111111111111111000 Q
0R
1S
1T
b00000000000000000000000000000000 U
b111111111000 V
1W
b00000000000000000000000100001001 [
#81
0W
#82
b00000000000000000000000100001010 #
b00000000000000000000000011111111 $
b00000000000000000000000000001100 E
b00000000000001011000010100010011 F
b0010011 G
1H
0I
b00000 K
b01010 L
b000000000101 M
b000000000000 N
1O
1P
b00000000000000000000000000000000 Q
1R
0S
0T
b000000000000 V
1W
b00000000000000000000000100001010 [
#83
0W
#84
b00000000000000000000000000000000 $
b00000000000000000000000100001010 /
b00000000000000000000000000010000 E
b00000000000101011000010110010011 F
b00001 K
b01011 L
b010000000101 M
b000000000001 N
b00000000000000000000000000000001 Q
b00000000000000000000000000000001 U
b000000000001 V
1W
b00000000000000000000000100001010 Y
b00000000000000000000000100001011 [
#85
0W
#86
b00000000000000000000000100001011 0
b00000000000000000000000000010100 E
b11111110011001011001100011100011 F
b1100011 G
0H
1I
b00110 K
b10001 L
b111111111000 M
b111111100110 N
0O
0P
b11111111111111111111111111111000 Q
0R
1S
1T
b00000000000000000000000000000000 U
b111111111000 V
1W
b00000000000000000000000100001010 [
#87
0W
